easy_xml/__init__.py
easy_xml-0.7.0.dist-info/LICENSE
easy_xml-0.7.0.dist-info/METADATA
easy_xml-0.7.0.dist-info/WHEEL
easy_xml-0.7.0.dist-info/top_level.txt
easy_xml-0.7.0.dist-info/RECORD
