Metadata-Version: 2.1
Name: easy-xml
Version: 0.7.0
Summary: EasyXML is a simple object representation of an XML document.
Home-page: https://github.com/darkfoxprime/python-easy_xml
Author: Johnson Earls
Author-email: johnson.earls@oracle.com
License: ISC
Keywords: xml
Classifier: Development Status :: 4 - Beta
Classifier: Intended Audience :: Developers
Classifier: License :: OSI Approved :: ISC License (ISCL)
Classifier: Operating System :: OS Independent
Classifier: Programming Language :: Python :: 2.3
Classifier: Programming Language :: Python :: 2.4
Classifier: Programming Language :: Python :: 2.5
Classifier: Programming Language :: Python :: 2.6
Classifier: Programming Language :: Python :: 2.7
Classifier: Programming Language :: Python :: 3.7
Classifier: Topic :: Software Development :: Libraries :: Python Modules
Classifier: Topic :: Text Processing :: Markup :: XML
License-File: LICENSE
